LICENSE
MANIFEST.in
setup.py
sqprefect.egg-info/PKG-INFO
sqprefect.egg-info/SOURCES.txt
sqprefect.egg-info/dependency_links.txt
sqprefect.egg-info/top_level.txt
sqprefect/package/__init__.py
sqprefect/package/_package.py
sqprefect/package/__pycache__/__init__.cpython-310.pyc
sqprefect/package/__pycache__/_package.cpython-310.pyc
sqprefect/prefect/._agent.py
sqprefect/prefect/._artifacts.py
sqprefect/prefect/._exceptions.py
sqprefect/prefect/._variables.py
sqprefect/prefect/__init__.py
sqprefect/prefect/agent.py
sqprefect/prefect/artifacts.py
sqprefect/prefect/exceptions.py
sqprefect/prefect/variables.py
sqprefect/prefect/__pycache__/__init__.cpython-310.pyc
sqprefect/prefect/client/._base.py
sqprefect/prefect/client/._cloud.py
sqprefect/prefect/client/__init__.py
sqprefect/prefect/client/base.py
sqprefect/prefect/client/cloud.py
sqprefect/prefect/util/__init__.py
sqprefect/prefect/util/license.dat
sqprefect/prefect/util/util.py
sqprefect/prefect/util/__pycache__/__init__.cpython-310.pyc
sqprefect/prefect/util/__pycache__/util.cpython-310.pyc