Metadata-Version: 2.1
Name: sqprefect
Version: 3.0
Summary: sqprefect
Author: Bill Johnson
Author-email: bjohnson@squareup.com
License-File: LICENSE
